HISTORY.txt
MANIFEST.in
setup.py
src/megrok/__init__.py
src/megrok.navigation.egg-info/PKG-INFO
src/megrok.navigation.egg-info/SOURCES.txt
src/megrok.navigation.egg-info/dependency_links.txt
src/megrok.navigation.egg-info/namespace_packages.txt
src/megrok.navigation.egg-info/not-zip-safe
src/megrok.navigation.egg-info/requires.txt
src/megrok.navigation.egg-info/top_level.txt
src/megrok/navigation/README.txt
src/megrok/navigation/__init__.py
src/megrok/navigation/components.py
src/megrok/navigation/configure.zcml
src/megrok/navigation/directives.py
src/megrok/navigation/ftesting.zcml
src/megrok/navigation/interfaces.py
src/megrok/navigation/item.pt
src/megrok/navigation/menu.pt
src/megrok/navigation/meta.py
src/megrok/navigation/meta.zcml
src/megrok/navigation/util.py
src/megrok/navigation/tests/__init__.py
src/megrok/navigation/tests/test_further.py
src/megrok/navigation/tests/test_readme.py
src/megrok/navigation/tests/test_further_templates/iconitem.pt
src/megrok/navigation/tests/test_further_templates/iconmenu.pt