Metadata-Version: 1.0
Name: megrok.navigation
Version: 0.6.2
Summary: Navigation Menus for Grok
Home-page: http://www.python.org/pypi/megrok.navigation
Author: Jeroen Michiel
Author-email: jmichiel@yahoo.com
License: UNKNOWN
Platform: Any
Classifier: Development Status :: 5 - Production/Stable
Classifier: Environment :: Web Environment
Classifier: Framework :: Zope3
Classifier: Intended Audience :: Other Audience
Classifier: License :: OSI Approved :: GNU General Public License (GPL)
Classifier: Operating System :: OS Independent
Classifier: Programming Language :: Python
